greenbids/tailor/core/__init__.py
greenbids/tailor/core/__main__.py
greenbids/tailor/core/_version.py
greenbids/tailor/core/fabric.py
greenbids/tailor/core/logging_.py
greenbids/tailor/core/models.py
greenbids/tailor/core/settings.py
greenbids/tailor/core/telemetry.py
greenbids/tailor/core/app/__init__.py
greenbids/tailor/core/app/exceptions.py
greenbids/tailor/core/app/main.py
greenbids/tailor/core/app/profiler.py
greenbids/tailor/core/app/resources.py
greenbids/tailor/core/app/tasks.py
greenbids/tailor/core/app/routers/__init__.py
greenbids/tailor/core/app/routers/healthz.py
greenbids/tailor/core/app/routers/ping.py
greenbids/tailor/core/app/routers/root.py
greenbids/tailor/load_testing/__init__.py
greenbids/tailor/load_testing/_utils.py
greenbids/tailor/load_testing/ping.py
greenbids/tailor/load_testing/probes.py
greenbids/tailor/load_testing/root.py
greenbids/tailor/load_testing/rtb.py
greenbids_tailor-0.5.1.dist-info/METADATA
greenbids_tailor-0.5.1.dist-info/WHEEL
greenbids_tailor-0.5.1.dist-info/entry_points.txt
greenbids_tailor-0.5.1.dist-info/RECORD
