Metadata-Version: 2.4
Name: greenbids-tailor
Version: 0.5.1
Summary: Bring traffic shaping to your own cloud
Project-URL: Repository, https://github.com/greenbids/greenbids-tailor-external.git
Author: greenbids.ai
License:                     GNU AFFERO GENERAL PUBLIC LICENSE
Keywords: adtech,openrtb,traffic shaping
Classifier: Development Status :: 4 - Beta
Classifier: Programming Language :: Python
Requires-Python: >=3.11
Requires-Dist: fastapi[standard]~=0.111
Requires-Dist: filelock~=3.16
Requires-Dist: opentelemetry-api~=1.25
Requires-Dist: opentelemetry-exporter-otlp-proto-http~=1.25
Requires-Dist: opentelemetry-exporter-prometheus~=0.48b0
Requires-Dist: opentelemetry-instrumentation-fastapi~=0.46b0
Requires-Dist: opentelemetry-sdk~=1.25
Requires-Dist: pydantic-settings~=2.8
Provides-Extra: load-testing
Requires-Dist: locust; extra == 'load-testing'
Requires-Dist: polyfactory; extra == 'load-testing'
